scanpydoc/__init__.py
scanpydoc/_types.py
scanpydoc/_version.py
scanpydoc/autosummary_generate_imported.py
scanpydoc/definition_list_typed_field.py
scanpydoc/py.typed
scanpydoc/release_notes.py
scanpydoc/testing.py
scanpydoc/elegant_typehints/__init__.py
scanpydoc/elegant_typehints/_autodoc_patch.py
scanpydoc/elegant_typehints/_formatting.py
scanpydoc/elegant_typehints/_return_tuple.py
scanpydoc/elegant_typehints/_role_mapping.py
scanpydoc/elegant_typehints/example.py
scanpydoc/rtd_github_links/__init__.py
scanpydoc/rtd_github_links/_linkcode.py
scanpydoc/rtd_github_links/_testdata.py
scanpydoc/theme/__init__.py
scanpydoc/theme/layout.html
scanpydoc/theme/theme.conf
scanpydoc/theme/static/scripts/rtd-sphinx-search.js
scanpydoc/theme/static/styles/scanpy.css
scanpydoc-0.17.1.dist-info/METADATA
scanpydoc-0.17.1.dist-info/WHEEL
scanpydoc-0.17.1.dist-info/entry_points.txt
scanpydoc-0.17.1.dist-info/licenses/LICENSE
scanpydoc-0.17.1.dist-info/RECORD
