Metadata-Version: 2.4
Name: scanpydoc
Version: 0.17.1
Summary: A series of Sphinx extensions to get maintainable numpydoc style documentation.
Project-URL: Source, https://github.com/theislab/scanpydoc/
Project-URL: Documentation, https://icb-scanpydoc.readthedocs-hosted.com/
Author-email: Philipp Angerer <phil.angerer@gmail.com>
License-Expression: GPL-3.0-or-later
License-File: LICENSE
Classifier: Framework :: Sphinx :: Extension
Classifier: Intended Audience :: Developers
Classifier: Programming Language :: Python :: 3
Classifier: Topic :: Documentation :: Sphinx
Classifier: Topic :: Software Development :: Libraries :: Python Modules
Classifier: Typing :: Typed
Requires-Python: >=3.12
Requires-Dist: sphinx>=7.0
Provides-Extra: dev
Requires-Dist: pre-commit; extra == 'dev'
Provides-Extra: doc
Requires-Dist: myst-parser; extra == 'doc'
Requires-Dist: sphinx; extra == 'doc'
Requires-Dist: sphinx-autodoc-typehints>=1.15.2; extra == 'doc'
Requires-Dist: sphinx-book-theme>=1.1.0; extra == 'doc'
Provides-Extra: myst
Requires-Dist: myst-parser; extra == 'myst'
Provides-Extra: test
Requires-Dist: coverage; extra == 'test'
Requires-Dist: defusedxml; extra == 'test'
Requires-Dist: legacy-api-wrap; extra == 'test'
Requires-Dist: pytest; extra == 'test'
Requires-Dist: sphinx>=8.1.0; extra == 'test'
Provides-Extra: theme
Requires-Dist: sphinx-book-theme>=1.1.0; extra == 'theme'
Provides-Extra: typehints
Requires-Dist: sphinx-autodoc-typehints>=1.15.2; extra == 'typehints'
